README.md
setup.py
matrix_conv/__init__.py
matrix_conv/matrix_conv.py
matrix_conv.egg-info/PKG-INFO
matrix_conv.egg-info/SOURCES.txt
matrix_conv.egg-info/dependency_links.txt
matrix_conv.egg-info/requires.txt
matrix_conv.egg-info/top_level.txt