Metadata-Version: 2.1
Name: matrix-conv
Version: 1.0.0
Summary: Graph convolutional operator that uses a CNN as a filter
Home-page: https://github.com/shobrook/MatrixConv
Author: shobrook
Author-email: shobrookj@gmail.com
License: MIT
Keywords: gnn,graph-neural-network,convolution,pytorch,graph,cnn,matrix,image
Platform: UNKNOWN
Requires-Python: >=3
